CensorIt/__init__.py
CensorIt/censorer.py
CensorIt-0.0.2.dist-info/LICENSE.txt
CensorIt-0.0.2.dist-info/METADATA
CensorIt-0.0.2.dist-info/WHEEL
CensorIt-0.0.2.dist-info/top_level.txt
CensorIt-0.0.2.dist-info/RECORD
