Metadata-Version: 2.1
Name: CensorIt
Version: 0.0.2
Summary: A Python Curse Word Censoring Package
Home-page: https://github.com/jack-the-hack/CensorIt
Author: Donnie Jack Baldyga
Author-email: jackedak@gmail.com
License: MIT License
Platform: UNKNOWN
Classifier: License :: OSI Approved :: MIT License
Classifier: Operating System :: OS Independent
Classifier: Programming Language :: Python :: 3
